lektor_i18n-0.5.0.dist-info/METADATA
lektor_i18n-0.5.0.dist-info/WHEEL
lektor_i18n-0.5.0.dist-info/entry_points.txt
lektor_i18n-0.5.0.dist-info/licenses/LICENSE
lektor_i18n.py
lektor_i18n-0.5.0.dist-info/RECORD
