Metadata-Version: 2.1
Name: lektor-i18n
Version: 0.5.0
Summary: A plugin for using GetText .PO files to translate Lektor sites content
Keywords: Lektor plugin
Author-Email: =?utf-8?b?SsOpcsO0bWUgQ2hhcmFvdWk=?= <jerome@riseup.net>, NumeriCube <support@numericube.com>
License:                     GNU GENERAL PUBLIC LICENSE
Classifier: Development Status :: 5 - Production/Stable
Classifier: Environment :: Plugins
Classifier: Environment :: Web Environment
Classifier: Framework :: Lektor
Classifier: Intended Audience :: Developers
Classifier: License :: OSI Approved :: GNU General Public License v3 or later (GPLv3+)
Classifier: Programming Language :: Python :: 3
Classifier: Programming Language :: Python :: 3.8
Classifier: Programming Language :: Python :: 3.9
Classifier: Programming Language :: Python :: 3.10
Classifier: Programming Language :: Python :: 3.11
Classifier: Programming Language :: Python :: 3.12
Classifier: Topic :: Text Processing
Classifier: Topic :: Software Development :: Internationalization
Project-URL: Home, https://github.com/numericube/lektor-i18n-plugin
Requires-Python: >=3.8
